internals.py
opensimplex_loops.py
opensimplex_loops-1.0.1.dist-info/AUTHORS.rst
opensimplex_loops-1.0.1.dist-info/LICENSE.txt
opensimplex_loops-1.0.1.dist-info/METADATA
opensimplex_loops-1.0.1.dist-info/WHEEL
opensimplex_loops-1.0.1.dist-info/top_level.txt
opensimplex_loops-1.0.1.dist-info/RECORD
