Metadata-Version: 2.1
Name: opensimplex-loops
Version: 1.0.1
Summary: Python library to generate seamlessly-looping animated images and closed curves, and seamlessy-tileable images. Based on 4D OpenSimplex noise.
Home-page: https://github.com/Dennis-van-Gils/opensimplex-loops
Author: Dennis van Gils
Author-email: vangils.dennis@gmail.com
License: MIT
Project-URL: Issue Tracker, https://github.com/Dennis-van-Gils/opensimplex-loops/issues
Keywords: opensimplex,noise,4D,polar,loop,looping,seamless,tileable,textures,images,curves
Classifier: License :: OSI Approved :: MIT License
Classifier: Intended Audience :: Developers
Classifier: Intended Audience :: Science/Research
Classifier: Operating System :: OS Independent
Classifier: Programming Language :: Python
Classifier: Programming Language :: Python :: 3.8
Classifier: Programming Language :: Python :: 3.9
Classifier: Programming Language :: Python :: 3.10
Classifier: Programming Language :: Python :: 3.11
Classifier: Programming Language :: Python :: 3.12
Classifier: Topic :: Scientific/Engineering :: Mathematics
Requires-Python: >=3.8
License-File: LICENSE.txt
License-File: AUTHORS.rst
Requires-Dist: opensimplex ~=0.4
Requires-Dist: numpy
Requires-Dist: numba
Requires-Dist: numba-progress
Provides-Extra: demos
Requires-Dist: matplotlib ; extra == 'demos'
Requires-Dist: pillow ; extra == 'demos'
